LICENSE
MANIFEST.in
README.rst
setup.py
steak.py
bin/grill
steak.egg-info/PKG-INFO
steak.egg-info/SOURCES.txt
steak.egg-info/dependency_links.txt
steak.egg-info/top_level.txt