Metadata-Version: 1.0
Name: steak
Version: 0.1.1
Summary: Simplify writing and executing repetitive tasks.
Home-page: https://github.com/scizzorz/steak
Author: John Weachock
Author-email: jweachock@gmail.com
License: MIT
Platform: UNKNOWN
